Metadata-Version: 1.1
Name: ObservableList
Version: 0.0.3
Summary: Python library for a list with an observer interface.
Home-page: https://github.com/niccokunzmann/ObservableList
Author: Nicco Kunzmann
Author-email: niccokunzmann@rambler.ru
License: LGPL
Keywords: knitting ayab fashion
Platform: UNKNOWN
Classifier: Intended Audience :: Developers
Classifier: License :: OSI Approved :: GNU Lesser General Public License v3 (LGPLv3)
Classifier: Topic :: Software Development :: Libraries :: Python Modules
Classifier: Topic :: Artistic Software
Classifier: Topic :: Home Automation
Classifier: Topic :: Utilities
Classifier: Intended Audience :: Manufacturing
Classifier: Natural Language :: English
Classifier: Operating System :: OS Independent
Classifier: Programming Language :: Python :: 2.6
Classifier: Programming Language :: Python :: 2.7
Classifier: Programming Language :: Python :: 3.3
Classifier: Programming Language :: Python :: 3.4
Classifier: Programming Language :: Python :: 3.5
Classifier: Development Status :: 5 - Production/Stable
